tfdevops/__init__.py
tfdevops/cfn.py
tfdevops/cli.py
tfdevops/resource.py
tfdevops/utils.py
tfdevops-0.1.1.dist-info/entry_points.txt
tfdevops-0.1.1.dist-info/WHEEL
tfdevops-0.1.1.dist-info/METADATA
tfdevops-0.1.1.dist-info/RECORD
